{
	"Jalen Green": "/players/g/greenja05",
	 "Alperen Şengün": "/players/s/sengual01",
	 "Fred VanVleet": "/players/v/vanvlfr01",
	 "Amen Thompson": "/players/t/thompam01",
	 "Dillon Brooks": "/players/b/brookdi01",
	 "Jabari Smith": "/players/s/smithja05",
	 "Aaron Holiday": "/players/h/holidaa01",
	 "Reed Sheppard": "/players/s/sheppre01",
	 "Steven Adams": "/players/a/adamsst01",
	 "Tari Eason": "/players/e/easonta01",
	 "Cam Whitmore": "/players/w/whitmca01",
	 "Jae'Sean Tate": "/players/t/tateja01",
	 "Jock Landale": "/players/l/landajo01",
	 "Jeff Green": "/players/g/greenje02",
	 "Jeenathan Williams": "/players/w/willije02",
	 "Jack McVeigh": "/players/m/mcveija01",
	 "N'Faly Dante": "/players/n/nfalyda01",
	 "Clint Capela": "/players/c/capelca01",
	 "Trae Young": "/players/y/youngtr01",
	 "Dyson Daniels": "/players/d/daniedy01",
	 "Onyeka Okongwu": "/players/o/okongon01",
	 "Zaccharie Risacher": "/players/r/risacza01",
	 "Garrison Mathews": "/players/m/mathega01",
	 "Jalen Johnson": "/players/j/johnsja05",
	 "De'Andre Hunter": "/players/h/huntede01",
	 "Vit Krejci": "/players/k/krejcvi01",
	 "David Roddy": "/players/r/roddyda01",
	 "Bogdan Bogdanović": "/players/b/bogdabo01",
	 "Keaton Wallace": "/players/w/wallake01",
	 "Larry Nance": "/players/n/nancela02",
	 "Kobe Bufkin": "/players/b/bufkiko01",
	 "Dominick Barlow": "/players/b/barlodo01",
	 "Mouhamed Gueye": "/players/g/gueyemo02",
	 "Daeqwon Plowden": "/players/p/plowdda01",
	 "Cody Zeller": "/players/z/zelleco01",
	 "Collin Sexton": "/players/s/sextoco01",
	 "Isaiah Collier": "/players/c/colliis01",
	 "Drew Eubanks": "/players/e/eubandr01",
	 "Keyonte George": "/players/g/georgke01",
	 "Walker Kessler": "/players/k/kesslwa01",
	 "Brice Sensabaugh": "/players/s/sensabr01",
	 "Kyle Filipowski": "/players/f/filipky01",
	 "Lauri Markkanen": "/players/m/markkla01",
	 "Johnny Juzang": "/players/j/juzanjo01",
	 "John Collins": "/players/c/collijo01",
	 "Cody Williams": "/players/w/willico04",
	 "Jordan Clarkson": "/players/c/clarkjo01",
	 "Svi Mykhailiuk": "/players/m/mykhasv01",
	 "Micah Potter": "/players/p/pottemi01",
	 "Patty Mills": "/players/m/millspa02",
	 "Elijah Harkless": "/players/h/harklej01",
	 "Taylor Hendricks": "/players/h/hendrta01",
	 "Oscar Tshiebwe": "/players/t/tshieos01",
	 "Buddy Hield": "/players/h/hieldbu01",
	 "Trayce Jackson-Davis": "/players/j/jackstr02",
	 "Andrew Wiggins": "/players/w/wiggian01",
	 "Kevon Looney": "/players/l/looneke01",
	 "Moses Moody": "/players/m/moodymo01",
	 "Stephen Curry": "/players/c/curryst01",
	 "Lindy Waters": "/players/w/waterli01",
	 "Gary Payton": "/players/p/paytoga02",
	 "Draymond Green": "/players/g/greendr01",
	 "Kyle Anderson": "/players/a/anderky01",
	 "Brandin Podziemski": "/players/p/podzibr01",
	 "Jonathan Kuminga": "/players/k/kuminjo01",
	 "Gui Santos": "/players/s/santogu01",
	 "Dennis Schröder": "/players/s/schrode01",
	 "Pat Spencer": "/players/s/spencpa01",
	 "Quinten Post": "/players/p/postqu01",
	 "Dalton Knecht": "/players/k/knechda01",
	 "Max Christie": "/players/c/chrisma02",
	 "Anthony Davis": "/players/d/davisan02",
	 "LeBron James": "/players/j/jamesle01",
	 "Austin Reaves": "/players/r/reaveau01",
	 "Gabe Vincent": "/players/v/vincega01",
	 "Rui Hachimura": "/players/h/hachiru01",
	 "Cam Reddish": "/players/r/reddica01",
	 "Christian Koloko": "/players/k/kolokch01",
	 "Jaxson Hayes": "/players/h/hayesja02",
	 "Bronny James": "/players/j/jamesbr02",
	 "Dorian Finney-Smith": "/players/f/finnedo01",
	 "Shake Milton": "/players/m/miltosh01",
	 "Armel Traoré": "/players/a/armeltr01",
	 "Jarred Vanderbilt": "/players/v/vandeja01",
	 "Jalen Hood-Schifino": "/players/h/hoodsja01",
	 "Trey Jemison": "/players/j/jemistr01",
	 "Christian Wood": "/players/w/woodch01",
	 "Guerschon Yabusele": "/players/y/yabusgu01",
	 "Kelly Oubre": "/players/o/oubreke01",
	 "Tyrese Maxey": "/players/m/maxeyty01",
	 "Ricky Council": "/players/c/councri01",
	 "Eric Gordon": "/players/g/gordoer01",
	 "Caleb Martin": "/players/m/martica02",
	 "Paul George": "/players/g/georgpa01",
	 "Adem Bona": "/players/b/bonaad01",
	 "Andre Drummond": "/players/d/drumman01",
	 "Kyle Lowry": "/players/l/lowryky01",
	 "Reggie Jackson": "/players/j/jacksre01",
	 "KJ Martin": "/players/m/martike04",
	 "Jared McCain": "/players/m/mccaija01",
	 "Jeff Dowtin": "/players/d/dowtije01",
	 "Justin Edwards": "/players/e/edwarju01",
	 "Joel Embiid": "/players/e/embiijo01",
	 "Pete Nance": "/players/n/nancepe01",
	 "Brook Lopez": "/players/l/lopezbr01",
	 "Taurean Prince": "/players/p/princta02",
	 "Andre Jackson": "/players/j/jacksan01",
	 "Bobby Portis": "/players/p/portibo01",
	 "Gary Trent": "/players/t/trentga02",
	 "Giannis Antetokounmpo": "/players/a/antetgi01",
	 "Damian Lillard": "/players/l/lillada01",
	 "A.J. Green": "/players/g/greenaj01",
	 "Ryan Rollins": "/players/r/rolliry01",
	 "Pat Connaughton": "/players/c/connapa01",
	 "Delon Wright": "/players/w/wrighde01",
	 "MarJon Beauchamp": "/players/b/beaucma01",
	 "Khris Middleton": "/players/m/middlkh01",
	 "Stanley Umude": "/players/u/umudest01",
	 "Tyler Smith": "/players/s/smithty02",
	 "Liam Robbins": "/players/r/robbili01",
	 "Chris Livingston": "/players/l/livinch01",
	 "AJ Johnson": "/players/j/johnsaj01",
	 "Toumani Camara": "/players/c/camarto01",
	 "Deni Avdija": "/players/a/avdijde01",
	 "Anfernee Simons": "/players/s/simonan01",
	 "Scoot Henderson": "/players/h/hendesc01",
	 "Shaedon Sharpe": "/players/s/sharpsh01",
	 "Kris Murray": "/players/m/murrakr01",
	 "Dalano Banton": "/players/b/bantoda01",
	 "Jerami Grant": "/players/g/grantje01",
	 "Donovan Clingan": "/players/c/clingdo01",
	 "Jabari Walker": "/players/w/walkeja01",
	 "Deandre Ayton": "/players/a/aytonde01",
	 "Rayan Rupert": "/players/r/ruperra01",
	 "Duop Reath": "/players/r/reathdu01",
	 "Robert Williams": "/players/w/williro04",
	 "Bryce McGowens": "/players/m/mcgowbr01",
	 "Justin Minaya": "/players/m/minayju01",
	 "Taze Moore": "/players/m/mooreta02",
	 "Matisse Thybulle": "/players/t/thybuma01"
}